Metadata-Version: 2.1
Name: nepali-embedding
Version: 0.1
Summary: UNKNOWN
Home-page: https://github.com/pudasainishushant/nepali_embedding
License: UNKNOWN
Platform: UNKNOWN
Classifier: Programming Language :: Python :: 3
Classifier: License :: OSI Approved :: MIT License
Classifier: Operating System :: OS Independent
Requires-Python: >=3.5
License-File: LICENSE.md
License-File: AUTHORS.md
Requires-Dist: transformers (==4.15.0)
Requires-Dist: scipy
Requires-Dist: torch
Requires-Dist: gensim (==4.1.2)
Requires-Dist: icu (==0.0.1)
Requires-Dist: scikit-learn (==0.24.2)
